lazylabel/__init__.py
lazylabel/_nbdev.py
lazylabel/basics.py
lazylabel/core.py
lazylabel/labeller/__init__.py
lazylabel/labeller/all.py
lazylabel/labeller/core.py
lazylabel/labeller/metrics.py
lazylabel/models/__init__.py
lazylabel/models/all.py
lazylabel/models/majority_label_voter.py
lazylabel/text/__init__.py
lazylabel/text/all.py
lazylabel/text/core.py
lazylabel/text/labellers.py
unknown/__init__.py
unknown/_nbdev.py
unknown/basics.py
unknown/core.py
unknown/labeller/__init__.py
unknown/labeller/all.py
unknown/labeller/core.py
unknown/labeller/metrics.py
unknown/models/__init__.py
unknown/models/all.py
unknown/models/majority_label_voter.py
unknown/text/__init__.py
unknown/text/all.py
unknown/text/core.py
unknown/text/labellers.py
lazylabel-0.0.1.dist-info/LICENSE
lazylabel-0.0.1.dist-info/METADATA
lazylabel-0.0.1.dist-info/WHEEL
lazylabel-0.0.1.dist-info/entry_points.txt
lazylabel-0.0.1.dist-info/top_level.txt
lazylabel-0.0.1.dist-info/RECORD
